fetch_leetcode_problem/__init__.py
fetch_leetcode_problem/_cookies.py
fetch_leetcode_problem/_func_parsing.py
fetch_leetcode_problem/_leetcode_api.py
fetch_leetcode_problem/_parsing.py
fetch_leetcode_problem/_problem_index.py
fetch_leetcode_problem/_util.py
fetch_leetcode_problem/main.py
fetch_leetcode_problem/problem_info.py
fetch_leetcode_problem/schema.sql
rossmassey_fetch_leetcode_problem-0.2.1.dist-info/METADATA
rossmassey_fetch_leetcode_problem-0.2.1.dist-info/WHEEL
rossmassey_fetch_leetcode_problem-0.2.1.dist-info/licenses/LICENSE
rossmassey_fetch_leetcode_problem-0.2.1.dist-info/RECORD
