Metadata-Version: 2.3
Name: rossmassey.fetch_leetcode_problem
Version: 0.2.1
Summary: A package for getting .rst formatted information and python code for a leetcode problem
Project-URL: Homepage, https://github.com/rossmassey/fetch-leetcode-problem
Project-URL: Documentation, https://rossmassey.github.io/fetch-leetcode-problem/
Project-URL: Issues, https://github.com/rossmassey/fetch-leetcode-problem/issues
Author-email: Ross Massey <massey0ross@gmail.com>
License-File: LICENSE
Classifier: License :: OSI Approved :: MIT License
Classifier: Operating System :: OS Independent
Classifier: Programming Language :: Python :: 3
Requires-Python: >=3.8
Requires-Dist: requests
